asmchip8/__init__.py
asmchip8/__main__.py
asmchip8/asm.py
asmchip8/assemblyerror.py
asmchip8/labeldef.py
asmchip8/lexer.py
asmchip8/operand.py
asmchip8/parser.py
asmchip8/statement.py
asmchip8/token.py
asmchip8/transdir.py
asmchip8/translator.py
asmchip8/transutil.py
asmchip8-0.1.data/data/share/man/man1/asmchip8.1
asmchip8-0.1.data/data/share/man/man5/asmchip8.5
asmchip8-0.1.dist-info/entry_points.txt
asmchip8-0.1.dist-info/WHEEL
asmchip8-0.1.dist-info/METADATA
asmchip8-0.1.dist-info/RECORD
