Metadata-Version: 2.1
Name: asmchip8
Version: 0.1
Summary: Assembler for CHIP-8.
Keywords: assembler,chip8
Author-email: Mariano Street <mctpyt@proton.me>
Requires-Python: >=3.10
Classifier: Development Status :: 3 - Alpha
Classifier: Environment :: Console
Classifier: Intended Audience :: Developers
Classifier: Intended Audience :: Education
Classifier: License :: OSI Approved :: GNU Affero General Public License v3 or later (AGPLv3+)
Classifier: Programming Language :: Python :: 3 :: Only
Classifier: Programming Language :: Python :: 3.10
Classifier: Programming Language :: Python :: 3.11
Classifier: Programming Language :: Python :: 3.12
Classifier: Operating System :: OS Independent
Classifier: Topic :: Software Development :: Assemblers
Classifier: Typing :: Typed
Project-URL: Home, https://gitlab.com/mctpyt/asmchip8
Project-URL: Manpages, https://gitlab.com/mctpyt/asmchip8/-/tree/master/doc
